sequence_annotation/__init__.py
sequence_annotation/sequence_annotation.py
sequence_annotation/clients/__init__.py
sequence_annotation/clients/mobidb_client.py
sequence_annotation/clients/sifts_client.py
sequence_annotation/clients/uniprot_client.py
sequence_annotation/dto/__init__.py
sequence_annotation/dto/chains.py
sequence_annotation/dto/protein.py
sequence_annotation/dto/residues.py
sequence_annotation/services/__init__.py
sequence_annotation/services/path_validation.py
sequence_annotation/services/proteins_search_service.py
sequence_annotation/utils/__init__.py
sequence_annotation/utils/pretty_print.py
test/__init__.py
sequence_annotation-0.0.8.dist-info/LICENSE
sequence_annotation-0.0.8.dist-info/METADATA
sequence_annotation-0.0.8.dist-info/WHEEL
sequence_annotation-0.0.8.dist-info/entry_points.txt
sequence_annotation-0.0.8.dist-info/top_level.txt
sequence_annotation-0.0.8.dist-info/RECORD
