Metadata-Version: 2.1
Name: sequence-annotation
Version: 0.0.8
Summary: Proteins info mapper
Home-page: https://github.com/BioinformaticaUNQ/sequence_annotation.git
Author: BioInformatico UNQ
Author-email: author@gmail.com
License: UNKNOWN
Platform: UNKNOWN
License-File: LICENSE
Requires-Dist: requests (>=2.13.0)
